pyzhuyin/__init__.py
pyzhuyin/_mapping.py
pyzhuyin/convert.py
pyzhuyin-0.0.3.dist-info/LICENSE
pyzhuyin-0.0.3.dist-info/METADATA
pyzhuyin-0.0.3.dist-info/WHEEL
pyzhuyin-0.0.3.dist-info/top_level.txt
pyzhuyin-0.0.3.dist-info/RECORD
