Metadata-Version: 2.1
Name: pyzhuyin
Version: 0.0.3
Summary: 注音和拼音的轉換工具
Home-page: https://github.com/rku1999/pyzhuyin
Author: Raymond Ku
License: UNKNOWN
Project-URL: Source, https://github.com/rku1999/pyzhuyin
Project-URL: Bug Tracker, https://github.com/rku1999/pyzhuyin/issues
Keywords: pinyin,zhuyin,拼音,注音
Platform: UNKNOWN
Classifier: Development Status :: 4 - Beta
Classifier: Intended Audience :: Developers
Classifier: Topic :: Utilities
Classifier: Topic :: Text Processing
Classifier: Programming Language :: Python :: 3
Classifier: License :: OSI Approved :: MIT License
Classifier: Operating System :: OS Independent
Requires-Python: >=3.6
License-File: LICENSE
